accapi/__init__.py
accapi/client.py
accapi/token.py
accapi-0.0.3.dist-info/LICENSE
accapi-0.0.3.dist-info/METADATA
accapi-0.0.3.dist-info/WHEEL
accapi-0.0.3.dist-info/top_level.txt
accapi-0.0.3.dist-info/RECORD
