Metadata-Version: 2.1
Name: accapi
Version: 0.0.3
Summary: Avigilon Control Center API for Python
Home-page: UNKNOWN
Author: Jakub Bartkowiak
Author-email: gralinpl@gmail.com
License: UNKNOWN
Project-URL: Source, https://github.com/gralin/acc-api-python
Keywords: python,acc,avigilon
Platform: UNKNOWN
Classifier: Programming Language :: Python :: 3
Classifier: License :: OSI Approved :: MIT License
Classifier: Operating System :: OS Independent
License-File: LICENSE
